ngspicehlp/__init__.py
ngspicehlp/analyses.py
ngspicehlp/control.py
ngspicehlp/kicad.py
ngspicehlp/mypy.ini
ngspicehlp/netlist.py
ngspicehlp/oscilloscope.mplstyle
ngspicehlp/plot.py
ngspicehlp/print_section.py
ngspicehlp/simulate.py
ngspicehlp/to_pandas.py
ngspicehlp/vectors.py
ngspicehlp/__pycache__/__init__.cpython-311.pyc
ngspicehlp/__pycache__/analyses.cpython-311.pyc
ngspicehlp/__pycache__/control.cpython-311.pyc
ngspicehlp/__pycache__/kicad.cpython-311.pyc
ngspicehlp/__pycache__/netlist.cpython-311.pyc
ngspicehlp/__pycache__/plot.cpython-311.pyc
ngspicehlp/__pycache__/print_section.cpython-311.pyc
ngspicehlp/__pycache__/simulate.cpython-311.pyc
ngspicehlp/__pycache__/test_kicad.cpython-311-pytest-7.2.1.pyc
ngspicehlp/__pycache__/to_pandas.cpython-311.pyc
ngspicehlp/__pycache__/vectors.cpython-311.pyc
ngspicehlp-0.0.1.dist-info/METADATA
ngspicehlp-0.0.1.dist-info/WHEEL
ngspicehlp-0.0.1.dist-info/top_level.txt
ngspicehlp-0.0.1.dist-info/RECORD
