Metadata-Version: 2.1
Name: ngspicehlp
Version: 0.0.1
Summary: ngspice helper
Author-email: Mark Chadwick <mark.chadwick@techsharpen.com>
License: MIT License
Project-URL: repository, https://github.com/astorguy/ngspicehlp_project
Keywords: ngspice,spice,simulation
Classifier: Programming Language :: Python :: 3
Requires-Python: >=3.11
